django_idfield-1.0.1.dist-info/DESCRIPTION.rst
django_idfield-1.0.1.dist-info/METADATA
django_idfield-1.0.1.dist-info/RECORD
django_idfield-1.0.1.dist-info/WHEEL
django_idfield-1.0.1.dist-info/metadata.json
django_idfield-1.0.1.dist-info/top_level.txt
idfield/__init__.py
idfield/fields.py
