Metadata-Version: 2.0
Name: django-idfield
Version: 1.0.1
Summary: Char ID filed Django
Home-page: https://github.com/lis-space/django-idfield
Author: Alex Lis
Author-email: a@lis.space
License: MIT
Platform: UNKNOWN
Classifier: Development Status :: 4 - Beta
Classifier: Framework :: Django
Classifier: Operating System :: OS Independent
Classifier: Programming Language :: Python :: 3
Classifier: License :: OSI Approved :: MIT License
Classifier: Intended Audience :: Developers
Requires-Python: >=3
Requires-Dist: django
